arcparse/__init__.py
arcparse/_argument_helpers.py
arcparse/_partial_arguments.py
arcparse/_typehints.py
arcparse/_validations.py
arcparse/arguments.py
arcparse/converters.py
arcparse/errors.py
arcparse/parser.py
arcparse/py.typed
arcparse/validations.py
arcparse-1.3.1.dist-info/LICENSE
arcparse-1.3.1.dist-info/METADATA
arcparse-1.3.1.dist-info/WHEEL
arcparse-1.3.1.dist-info/RECORD
