Metadata-Version: 2.1
Name: arcparse
Version: 1.3.1
Summary: Declare program arguments in a type-safe way
Home-page: https://github.com/Kuba314/arcparse
License: MIT
Keywords: argparse,declarative,argument,parsing,type-safe
Author: Jakub Rozek
Author-email: jakub.rozek314@gmail.com
Requires-Python: >=3.12,<4.0
Classifier: License :: OSI Approved :: MIT License
Classifier: Programming Language :: Python :: 3
Classifier: Programming Language :: Python :: 3.12
Classifier: Programming Language :: Python :: 3.13
Classifier: Topic :: Software Development :: Libraries :: Python Modules
Classifier: Topic :: Utilities
Classifier: Typing :: Typed
Project-URL: Repository, https://github.com/Kuba314/arcparse
